format_blocks/__init__.py
format_blocks/base.py
format_blocks/blocks.py
format_blocks/extras.py
format_blocks/py.typed
format_blocks/support.py
format_blocks-0.1.2.dist-info/LICENSE
format_blocks-0.1.2.dist-info/WHEEL
format_blocks-0.1.2.dist-info/METADATA
format_blocks-0.1.2.dist-info/RECORD
