Metadata-Version: 2.1
Name: format-blocks
Version: 0.1.2
Summary: A library for building code formatters
Home-page: https://github.com/Spacerat/format-blocks
Author: Joseph Atkins-Turkish
Author-email: spacerat3004@gmail.com
Requires-Python: >=3.6,<4.0
Classifier: Programming Language :: Python :: 3
Classifier: Programming Language :: Python :: 3.6
Classifier: Programming Language :: Python :: 3.7
Classifier: Programming Language :: Python :: 3.8
Requires-Dist: typing_extensions (>=3.7.4,<4.0.0)
Project-URL: Repository, https://github.com/Spacerat/format-blocks
